LICENSE
MANIFEST.in
README.md
setup.py
bosunplugins/__init__.py
bosunplugins/devices.py
bosunplugins/util.py
bosunplugins.egg-info/PKG-INFO
bosunplugins.egg-info/SOURCES.txt
bosunplugins.egg-info/dependency_links.txt
bosunplugins.egg-info/not-zip-safe
bosunplugins.egg-info/top_level.txt
bosunplugins/listeners/__init__.py
bosunplugins/listeners/base.py
bosunplugins/listeners/ftp.py
bosunplugins/listeners/http.py