Metadata-Version: 1.1
Name: bosunplugins
Version: 0.1.0
Summary: Plugin framework for Bosun and Crowsnest, of http://www.crowsnest.io
Home-page: UNKNOWN
Author: Ian A Wilson
Author-email: UNKNOWN
License: UNKNOWN
Platform: UNKNOWN
Classifier: Intended Audience :: Developers
Classifier: Intended Audience :: Information Technology
Classifier: License :: OSI Approved :: MIT License
Classifier: Programming Language :: Python
